{
    "bodies": [
        {
            "name": "body0",
            "userData": "",
            "texture": "",
            "spriteData": [],
            "initialSpriteData": [],
            "shapes": [
                {
                    "shapeType": 0,
                    "position": [
                        335,
                        -49
                    ],
                    "scaleXY": [
                        21.499796653643077,
                        0.26157248664132127
                    ],
                    "rotation": 0,
                    "vertices": [
                        {
                            "x": -739.9898326821531,
                            "y": -62.078624332065964,
                            "width": 10,
                            "height": 10,
                            "isSelected": false
                        },
                        {
                            "x": 1409.989832682153,
                            "y": -62.078624332066056,
                            "width": 10,
                            "height": 10,
                            "isSelected": false
                        },
                        {
                            "x": 1409.989832682153,
                            "y": -35.92137566793397,
                            "width": 10,
                            "height": 10,
                            "isSelected": false
                        },
                        {
                            "x": -739.9898326821531,
                            "y": -35.921375667934036,
                            "width": 10,
                            "height": 10,
                            "isSelected": false
                        }
                    ],
                    "bounds": [
                        335,
                        -49.000000000000014,
                        2149.979665364306,
                        26.157248664132084
                    ],
                    "centroid": [
                        335,
                        -49.00000000000001
                    ],
                    "isSelected": false,
                    "inEditMode": false,
                    "friction": 1,
                    "restitution": 0.25,
                    "density": 1,
                    "isSensor": false,
                    "maskBits": 65535,
                    "categoryBits": 1,
                    "groupIndex": 0,
                    "width": 2149.979665364306,
                    "height": 26.15724866413209
                }
            ],
            "position": [
                335,
                -49
            ],
            "scaleXY": [
                21.499796653643077,
                0.26157248664132127
            ],
            "rotation": 0,
            "bounds": [
                335,
                -49.000000000000014,
                2149.979665364306,
                26.157248664132084
            ],
            "isSelected": false,
            "bodyType": "0",
            "isBullet": false,
            "isFixedRotation": false,
            "linearDamping": 0,
            "angularDamping": 0
        },
        {
            "name": "body1",
            "userData": "",
            "texture": "",
            "spriteData": [],
            "initialSpriteData": [],
            "shapes": [
                {
                    "shapeType": 0,
                    "position": [
                        373,
                        -191
                    ],
                    "scaleXY": [
                        2.558133155056767,
                        0.6674680179197443
                    ],
                    "rotation": 0,
                    "vertices": [
                        {
                            "x": 245.09334224716173,
                            "y": -224.3734008959872,
                            "width": 10,
                            "height": 10,
                            "isSelected": false
                        },
                        {
                            "x": 500.90665775283827,
                            "y": -224.3734008959872,
                            "width": 10,
                            "height": 10,
                            "isSelected": false
                        },
                        {
                            "x": 500.90665775283827,
                            "y": -157.6265991040128,
                            "width": 10,
                            "height": 10,
                            "isSelected": false
                        },
                        {
                            "x": 245.09334224716173,
                            "y": -157.6265991040128,
                            "width": 10,
                            "height": 10,
                            "isSelected": false
                        }
                    ],
                    "bounds": [
                        373,
                        -191,
                        255.81331550567654,
                        66.7468017919744
                    ],
                    "centroid": [
                        373,
                        -191
                    ],
                    "isSelected": false,
                    "inEditMode": false,
                    "friction": 1,
                    "restitution": 0.25,
                    "density": 1,
                    "isSensor": false,
                    "maskBits": 65535,
                    "categoryBits": 1,
                    "groupIndex": 0,
                    "width": 255.8133155056765,
                    "height": 66.7468017919744
                }
            ],
            "position": [
                373,
                -191
            ],
            "scaleXY": [
                2.558133155056767,
                0.6674680179197443
            ],
            "rotation": 0,
            "bounds": [
                373,
                -191,
                255.81331550567654,
                66.7468017919744
            ],
            "isSelected": false,
            "bodyType": 2,
            "isBullet": false,
            "isFixedRotation": false,
            "linearDamping": 0,
            "angularDamping": 0
        },
        {
            "name": "body2",
            "userData": "",
            "texture": "",
            "spriteData": [],
            "initialSpriteData": [],
            "shapes": [
                {
                    "shapeType": 1,
                    "position": [
                        459,
                        -107
                    ],
                    "scaleXY": [
                        0.6845661237403387,
                        0.6181458514486986
                    ],
                    "rotation": 0,
                    "vertices": [
                        {
                            "x": 493.2283061870169,
                            "y": -107,
                            "width": 10,
                            "height": 10,
                            "isSelected": false
                        },
                        {
                            "x": 486.6912813939658,
                            "y": -86.88110641232025,
                            "width": 10,
                            "height": 10,
                            "isSelected": false
                        },
                        {
                            "x": 469.5771283004574,
                            "y": -74.44694635909184,
                            "width": 10,
                            "height": 10,
                            "isSelected": false
                        },
                        {
                            "x": 448.4228716995426,
                            "y": -74.44694635909184,
                            "width": 10,
                            "height": 10,
                            "isSelected": false
                        },
                        {
                            "x": 431.3087186060342,
                            "y": -86.88110641232024,
                            "width": 10,
                            "height": 10,
                            "isSelected": false
                        },
                        {
                            "x": 424.7716938129831,
                            "y": -107,
                            "width": 10,
                            "height": 10,
                            "isSelected": false
                        },
                        {
                            "x": 431.3087186060342,
                            "y": -127.11889358767976,
                            "width": 10,
                            "height": 10,
                            "isSelected": false
                        },
                        {
                            "x": 448.4228716995426,
                            "y": -139.55305364090816,
                            "width": 10,
                            "height": 10,
                            "isSelected": false
                        },
                        {
                            "x": 469.5771283004574,
                            "y": -139.55305364090816,
                            "width": 10,
                            "height": 10,
                            "isSelected": false
                        },
                        {
                            "x": 486.6912813939658,
                            "y": -127.11889358767976,
                            "width": 10,
                            "height": 10,
                            "isSelected": false
                        }
                    ],
                    "bounds": [
                        459,
                        -107,
                        68.45661237403385,
                        65.10610728181632
                    ],
                    "centroid": [
                        459.0000000000001,
                        -107
                    ],
                    "isSelected": false,
                    "inEditMode": false,
                    "friction": 1,
                    "restitution": 0.25,
                    "density": 1,
                    "isSensor": false,
                    "maskBits": 65535,
                    "categoryBits": 1,
                    "groupIndex": 0,
                    "radius": 34.22830618701692
                }
            ],
            "position": [
                459,
                -107
            ],
            "scaleXY": [
                0.6845661237403387,
                0.6181458514486986
            ],
            "rotation": 0,
            "bounds": [
                459,
                -107,
                68.45661237403385,
                65.10610728181632
            ],
            "isSelected": false,
            "bodyType": 2,
            "isBullet": false,
            "isFixedRotation": false,
            "linearDamping": 0,
            "angularDamping": 0
        },
        {
            "name": "body3",
            "userData": "",
            "texture": "",
            "spriteData": [],
            "initialSpriteData": [],
            "shapes": [
                {
                    "shapeType": 1,
                    "position": [
                        295,
                        -107
                    ],
                    "scaleXY": [
                        0.6845661237403387,
                        0.6181458514486986
                    ],
                    "rotation": 0,
                    "vertices": [
                        {
                            "x": 329.2283061870169,
                            "y": -107,
                            "width": 10,
                            "height": 10,
                            "isSelected": false
                        },
                        {
                            "x": 322.6912813939658,
                            "y": -86.88110641232025,
                            "width": 10,
                            "height": 10,
                            "isSelected": false
                        },
                        {
                            "x": 305.5771283004574,
                            "y": -74.44694635909184,
                            "width": 10,
                            "height": 10,
                            "isSelected": false
                        },
                        {
                            "x": 284.4228716995426,
                            "y": -74.44694635909184,
                            "width": 10,
                            "height": 10,
                            "isSelected": false
                        },
                        {
                            "x": 267.3087186060342,
                            "y": -86.88110641232024,
                            "width": 10,
                            "height": 10,
                            "isSelected": false
                        },
                        {
                            "x": 260.7716938129831,
                            "y": -107,
                            "width": 10,
                            "height": 10,
                            "isSelected": false
                        },
                        {
                            "x": 267.3087186060342,
                            "y": -127.11889358767976,
                            "width": 10,
                            "height": 10,
                            "isSelected": false
                        },
                        {
                            "x": 284.4228716995426,
                            "y": -139.55305364090816,
                            "width": 10,
                            "height": 10,
                            "isSelected": false
                        },
                        {
                            "x": 305.5771283004574,
                            "y": -139.55305364090816,
                            "width": 10,
                            "height": 10,
                            "isSelected": false
                        },
                        {
                            "x": 322.6912813939658,
                            "y": -127.11889358767976,
                            "width": 10,
                            "height": 10,
                            "isSelected": false
                        }
                    ],
                    "bounds": [
                        295,
                        -107,
                        68.45661237403385,
                        65.10610728181632
                    ],
                    "centroid": [
                        295,
                        -107
                    ],
                    "isSelected": false,
                    "inEditMode": false,
                    "friction": 1,
                    "restitution": 0.25,
                    "density": 1,
                    "isSensor": false,
                    "maskBits": 65535,
                    "categoryBits": 1,
                    "groupIndex": 0,
                    "radius": 34.22830618701692
                }
            ],
            "position": [
                295,
                -107
            ],
            "scaleXY": [
                0.6845661237403387,
                0.6181458514486986
            ],
            "rotation": 0,
            "bounds": [
                295,
                -107,
                68.45661237403385,
                65.10610728181632
            ],
            "isSelected": false,
            "bodyType": 2,
            "isBullet": false,
            "isFixedRotation": false,
            "linearDamping": 0,
            "angularDamping": 0
        },
        {
            "name": "body4",
            "userData": "",
            "texture": "",
            "spriteData": [],
            "initialSpriteData": [],
            "shapes": [
                {
                    "shapeType": 0,
                    "position": [
                        311,
                        -307
                    ],
                    "scaleXY": [
                        0.8149136533058622,
                        0.6891695559255269
                    ],
                    "rotation": 0,
                    "vertices": [
                        {
                            "x": 270.2543173347069,
                            "y": -341.4584777962764,
                            "width": 10,
                            "height": 10,
                            "isSelected": false
                        },
                        {
                            "x": 351.7456826652931,
                            "y": -341.4584777962764,
                            "width": 10,
                            "height": 10,
                            "isSelected": false
                        },
                        {
                            "x": 351.7456826652931,
                            "y": -272.5415222037236,
                            "width": 10,
                            "height": 10,
                            "isSelected": false
                        },
                        {
                            "x": 270.2543173347069,
                            "y": -272.5415222037236,
                            "width": 10,
                            "height": 10,
                            "isSelected": false
                        }
                    ],
                    "bounds": [
                        311,
                        -307,
                        81.49136533058618,
                        68.91695559255277
                    ],
                    "centroid": [
                        311,
                        -307
                    ],
                    "isSelected": false,
                    "inEditMode": false,
                    "friction": 1,
                    "restitution": 0.25,
                    "density": 1,
                    "isSensor": false,
                    "maskBits": 65535,
                    "categoryBits": 1,
                    "groupIndex": 0,
                    "width": 81.49136533058622,
                    "height": 68.9169555925527
                }
            ],
            "position": [
                311,
                -307
            ],
            "scaleXY": [
                0.8149136533058622,
                0.6891695559255269
            ],
            "rotation": 0,
            "bounds": [
                311,
                -307,
                81.49136533058618,
                68.91695559255277
            ],
            "isSelected": false,
            "bodyType": 2,
            "isBullet": false,
            "isFixedRotation": false,
            "linearDamping": 0,
            "angularDamping": 0
        },
        {
            "name": "body5",
            "userData": "",
            "texture": "",
            "spriteData": [],
            "initialSpriteData": [],
            "shapes": [
                {
                    "shapeType": 0,
                    "position": [
                        453,
                        -310
                    ],
                    "scaleXY": [
                        0.8149136533058622,
                        0.6891695559255269
                    ],
                    "rotation": 0,
                    "vertices": [
                        {
                            "x": 412.2543173347069,
                            "y": -344.4584777962764,
                            "width": 10,
                            "height": 10,
                            "isSelected": false
                        },
                        {
                            "x": 493.7456826652931,
                            "y": -344.4584777962764,
                            "width": 10,
                            "height": 10,
                            "isSelected": false
                        },
                        {
                            "x": 493.7456826652931,
                            "y": -275.5415222037236,
                            "width": 10,
                            "height": 10,
                            "isSelected": false
                        },
                        {
                            "x": 412.2543173347069,
                            "y": -275.5415222037236,
                            "width": 10,
                            "height": 10,
                            "isSelected": false
                        }
                    ],
                    "bounds": [
                        453,
                        -310,
                        81.49136533058618,
                        68.91695559255277
                    ],
                    "centroid": [
                        453,
                        -310
                    ],
                    "isSelected": false,
                    "inEditMode": false,
                    "friction": 1,
                    "restitution": 0.25,
                    "density": 1,
                    "isSensor": false,
                    "maskBits": 65535,
                    "categoryBits": 1,
                    "groupIndex": 0,
                    "width": 81.49136533058622,
                    "height": 68.9169555925527
                }
            ],
            "position": [
                453,
                -310
            ],
            "scaleXY": [
                0.8149136533058622,
                0.6891695559255269
            ],
            "rotation": 0,
            "bounds": [
                453,
                -310,
                81.49136533058618,
                68.91695559255277
            ],
            "isSelected": false,
            "bodyType": 2,
            "isBullet": false,
            "isFixedRotation": false,
            "linearDamping": 0,
            "angularDamping": 0
        }
    ],
    "joints": [
        {
            "bodyIndexA": 1,
            "bodyIndexB": 3,
            "localAnchorA": [
                295,
                -107
            ],
            "localAnchorB": [
                295,
                -107
            ],
            "userData": "",
            "collideConnected": false,
            "jointType": 2,
            "position": [
                334,
                -149
            ],
            "scaleXY": [
                1,
                1
            ],
            "isSelected": false,
            "inEditMode": false,
            "name": "joint0",
            "enableLimit": false,
            "enableMotor": false,
            "lowerAngle": 0,
            "maxMotorTorque": 100,
            "motorSpeed": 100,
            "referenceAngle": 0,
            "upperAngle": 0
        },
        {
            "bodyIndexA": 1,
            "bodyIndexB": 2,
            "localAnchorA": [
                459,
                -107
            ],
            "localAnchorB": [
                459,
                -107
            ],
            "userData": "",
            "collideConnected": false,
            "jointType": 2,
            "position": [
                416,
                -149
            ],
            "scaleXY": [
                1,
                1
            ],
            "isSelected": false,
            "inEditMode": false,
            "name": "joint1",
            "enableLimit": false,
            "enableMotor": false,
            "lowerAngle": 0,
            "maxMotorTorque": 100,
            "motorSpeed": 100,
            "referenceAngle": 0,
            "upperAngle": 0
        },
        {
            "bodyIndexA": 1,
            "bodyIndexB": 4,
            "localAnchorA": [
                311,
                -305
            ],
            "localAnchorB": [
                311,
                -305
            ],
            "userData": "",
            "collideConnected": false,
            "jointType": 2,
            "position": [
                342,
                -248
            ],
            "scaleXY": [
                1,
                1
            ],
            "isSelected": false,
            "inEditMode": false,
            "name": "joint2",
            "enableLimit": false,
            "enableMotor": true,
            "lowerAngle": 0,
            "maxMotorTorque": 100,
            "motorSpeed": -2,
            "referenceAngle": 0,
            "upperAngle": 0
        },
        {
            "bodyIndexA": 4,
            "bodyIndexB": 3,
            "localAnchorA": [
                311,
                -305
            ],
            "localAnchorB": [
                295,
                -107
            ],
            "userData": "",
            "collideConnected": false,
            "jointType": 5,
            "position": [
                303,
                -206
            ],
            "scaleXY": [
                1,
                1
            ],
            "isSelected": false,
            "inEditMode": false,
            "name": "joint3",
            "joint1": {
                "bodyIndexA": 1,
                "bodyIndexB": 3,
                "localAnchorA": [
                    295,
                    -107
                ],
                "localAnchorB": [
                    295,
                    -107
                ],
                "userData": "",
                "collideConnected": false,
                "jointType": 2,
                "position": [
                    334,
                    -149
                ],
                "scaleXY": [
                    1,
                    1
                ],
                "isSelected": false,
                "inEditMode": false,
                "name": "joint0",
                "enableLimit": false,
                "enableMotor": false,
                "lowerAngle": 0,
                "maxMotorTorque": 100,
                "motorSpeed": 100,
                "referenceAngle": 0,
                "upperAngle": 0
            },
            "joint2": {
                "bodyIndexA": 1,
                "bodyIndexB": 4,
                "localAnchorA": [
                    311,
                    -305
                ],
                "localAnchorB": [
                    311,
                    -305
                ],
                "userData": "",
                "collideConnected": false,
                "jointType": 2,
                "position": [
                    342,
                    -248
                ],
                "scaleXY": [
                    1,
                    1
                ],
                "isSelected": false,
                "inEditMode": false,
                "name": "joint2",
                "enableLimit": false,
                "enableMotor": true,
                "lowerAngle": 0,
                "maxMotorTorque": 100,
                "motorSpeed": -2,
                "referenceAngle": 0,
                "upperAngle": 0
            },
            "frequencyHZ": 1,
            "jointIndex1": 0,
            "jointIndex2": 2
        },
        {
            "bodyIndexA": 1,
            "bodyIndexB": 5,
            "localAnchorA": [
                453,
                -310
            ],
            "localAnchorB": [
                453,
                -310
            ],
            "userData": "",
            "collideConnected": false,
            "jointType": 2,
            "position": [
                413,
                -250.5
            ],
            "scaleXY": [
                1,
                1
            ],
            "isSelected": false,
            "inEditMode": false,
            "name": "joint4",
            "enableLimit": false,
            "enableMotor": false,
            "lowerAngle": 0,
            "maxMotorTorque": 100,
            "motorSpeed": 100,
            "referenceAngle": 0,
            "upperAngle": 0
        },
        {
            "bodyIndexA": 5,
            "bodyIndexB": 2,
            "localAnchorA": [
                453,
                -310
            ],
            "localAnchorB": [
                459,
                -107
            ],
            "userData": "",
            "collideConnected": false,
            "jointType": 5,
            "position": [
                456,
                -208.5
            ],
            "scaleXY": [
                1,
                1
            ],
            "isSelected": false,
            "inEditMode": false,
            "name": "joint5",
            "joint1": {
                "bodyIndexA": 1,
                "bodyIndexB": 2,
                "localAnchorA": [
                    459,
                    -107
                ],
                "localAnchorB": [
                    459,
                    -107
                ],
                "userData": "",
                "collideConnected": false,
                "jointType": 2,
                "position": [
                    416,
                    -149
                ],
                "scaleXY": [
                    1,
                    1
                ],
                "isSelected": false,
                "inEditMode": false,
                "name": "joint1",
                "enableLimit": false,
                "enableMotor": false,
                "lowerAngle": 0,
                "maxMotorTorque": 100,
                "motorSpeed": 100,
                "referenceAngle": 0,
                "upperAngle": 0
            },
            "joint2": {
                "bodyIndexA": 1,
                "bodyIndexB": 5,
                "localAnchorA": [
                    453,
                    -310
                ],
                "localAnchorB": [
                    453,
                    -310
                ],
                "userData": "",
                "collideConnected": false,
                "jointType": 2,
                "position": [
                    413,
                    -250.5
                ],
                "scaleXY": [
                    1,
                    1
                ],
                "isSelected": false,
                "inEditMode": false,
                "name": "joint4",
                "enableLimit": false,
                "enableMotor": false,
                "lowerAngle": 0,
                "maxMotorTorque": 100,
                "motorSpeed": 100,
                "referenceAngle": 0,
                "upperAngle": 0
            },
            "frequencyHZ": 1,
            "jointIndex1": 1,
            "jointIndex2": 4
        }
    ]
}